{
  "forge_marker": 1,
  "defaults": {
    "model": "elementtimes:block/wire/element/point"
  },
  "variants": {
    "up": {
      "false": {},
      "true": {
        "submodel": "elementtimes:wire/element/north",
        "x": 270
      }
    },
    "down": {
      "false": {},
      "true": {
        "submodel": "elementtimes:wire/element/north",
        "x": 90
      }
    },
    "south": {
      "false": {},
      "true": {
        "submodel": "elementtimes:wire/element/north",
        "y": 180
      }
    },
    "north": {
      "false": {},
      "true": {
        "submodel": "elementtimes:wire/element/north"
      }
    },
    "west": {
      "false": {},
      "true": {
        "submodel": "elementtimes:wire/element/north",
        "y": 270
      }
    },
    "east": {
      "false": {},
      "true": {
        "submodel": "elementtimes:wire/element/north",
        "y": 90
      }
    }
  }
}